crimm_dock/DXGridUtil.py
crimm_dock/FFTDocker.py
crimm_dock/GridGenerator.py
crimm_dock/GridShapes.py
crimm_dock/__init__.py
crimm_dock/fft_docking.cpython-39-x86_64-linux-gnu.so
crimm_dock/Data/quaternion-1.npy
crimm_dock/Data/quaternion-2.npy
crimm_dock/Data/quaternion-3.npy
crimm_dock-2025.8a2.dist-info/licenses/LICENSE
crimm_dock-2025.8a2.dist-info/METADATA
crimm_dock-2025.8a2.dist-info/WHEEL
crimm_dock-2025.8a2.dist-info/top_level.txt
crimm_dock-2025.8a2.dist-info/RECORD
