Metadata-Version: 2.4
Name: crimm-dock
Version: 2025.8a2
Summary: Docking Module for Chemistry with the ReInvented Macromolecular
Author-email: Truman Xu <ziqiaoxu@umich.edu>
Project-URL: Homepage, https://github.com/Truman-Xu/crimm-dock
Project-URL: Bug Tracker, https://github.com/Truman-Xu/crimm-dock/issues
Classifier: Programming Language :: Python :: 3
Classifier: License :: OSI Approved :: GNU General Public License v3 (GPLv3)
Classifier: Operating System :: OS Independent
Classifier: Development Status :: 2 - Pre-Alpha
Requires-Python: >=3.8
License-File: LICENSE
Requires-Dist: crimm
Requires-Dist: scikit-learn
Dynamic: license-file
